models/__init__.py
models/three_layer_conv_net.py
models/three_layer_mlp.py
visunn/__init__.py
visunn/constants.py
visunn/main.py
visunn/modu.py
visunn/plot.py
visunn/util.py
visunn/visu.py
visunn/backend/__init__.py
visunn/backend/app.py
visunn/backend/routes.py
visunn/frontend/build/asset-manifest.json
visunn/frontend/build/favicon.ico
visunn/frontend/build/index.html
visunn/frontend/build/logo192.png
visunn/frontend/build/logo512.png
visunn/frontend/build/manifest.json
visunn/frontend/build/precache-manifest.10febd8ecf9ba159664f081a5cd31944.js
visunn/frontend/build/robots.txt
visunn/frontend/build/service-worker.js
visunn/frontend/build/static/css/main.5b292645.chunk.css
visunn/frontend/build/static/css/main.5b292645.chunk.css.map
visunn/frontend/build/static/js/2.5c24ba71.chunk.js
visunn/frontend/build/static/js/2.5c24ba71.chunk.js.LICENSE.txt
visunn/frontend/build/static/js/2.5c24ba71.chunk.js.map
visunn/frontend/build/static/js/main.76cd4042.chunk.js
visunn/frontend/build/static/js/main.76cd4042.chunk.js.map
visunn/frontend/build/static/js/runtime-main.1f1f19a3.js
visunn/frontend/build/static/js/runtime-main.1f1f19a3.js.map
visunn-0.1.1.dist-info/LICENSE
visunn-0.1.1.dist-info/METADATA
visunn-0.1.1.dist-info/WHEEL
visunn-0.1.1.dist-info/entry_points.txt
visunn-0.1.1.dist-info/top_level.txt
visunn-0.1.1.dist-info/RECORD
