Metadata-Version: 2.1
Name: visunn
Version: 0.1.1
Summary: visunn: aesthetic visualization of neural networks 
Home-page: https://github.com/vliu15/visunn
Author: Vincent Liu
Author-email: vliu15@stanford.edu
License: MIT
Keywords: deep learning visualization neural networks pytorch torch
Platform: UNKNOWN
Classifier: Intended Audience :: Developers
Classifier: Intended Audience :: Education
Classifier: Intended Audience :: Science/Research
Classifier: License :: OSI Approved :: MIT License
Classifier: Programming Language :: Python :: 3.5
Classifier: Programming Language :: Python :: 3.6
Classifier: Programming Language :: Python :: 3.7
Classifier: Topic :: Scientific/Engineering
Classifier: Topic :: Scientific/Engineering :: Mathematics
Classifier: Topic :: Scientific/Engineering :: Artificial Intelligence
Classifier: Topic :: Software Development
Classifier: Topic :: Software Development :: Libraries
Classifier: Topic :: Software Development :: Libraries :: Python Modules
Requires-Python: >=3.5
Requires-Dist: torch (>=1.4.0)
Requires-Dist: numpy (>=1.15.1)
Requires-Dist: pydot (>=1.4.1)
Requires-Dist: networkx (>=2.4)
Requires-Dist: protobuf (>=3.11.3)
Requires-Dist: flask (>=1.1.1)
Requires-Dist: flask-cors (>=3.0.8)
Requires-Dist: gevent (>=20.4.0)
